veloxdb.cpython-312-x86_64-linux-gnu.so
veloxdb-0.1.0.dist-info/METADATA
veloxdb-0.1.0.dist-info/WHEEL
veloxdb-0.1.0.dist-info/RECORD
veloxdb-0.1.0.dist-info/licenses/LICENSE
