Metadata-Version: 2.2
Name: veloxdb
Version: 0.1.0
Summary: A high performance embedded vector database written in C++ with AVX2 Support
Author-Email: Pranav Bhat <pranavbhat2004@gmail.com>
License: MIT
Classifier: Programming Language :: Python :: 3
Classifier: Programming Language :: C++
Classifier: Operating System :: POSIX :: Linux
Classifier: Operating System :: Microsoft :: Windows
Classifier: Topic :: Scientific/Engineering :: Artificial Intelligence
Requires-Python: >=3.9
